{
	"$schema": "http://schema.management.azure.com/schemas/2015-01-01/deploymentTemplate.json#",
	"contentVersion": "1.0.0.0",
	"parameters": {
		"factoryName": {
			"type": "string",
			"metadata": "Data Factory name",
			"defaultValue": "firstclass-adf-01"
		},
		"Ls_increment_load_connectionString": {
			"type": "secureString",
			"metadata": "Secure string for 'connectionString' of 'Ls_increment_load'"
		},
		"ls_1_connectionString": {
			"type": "secureString",
			"metadata": "Secure string for 'connectionString' of 'ls_1'"
		},
		"ls_incremental_load_password": {
			"type": "secureString",
			"metadata": "Secure string for 'password' of 'ls_incremental_load'"
		},
		"ls_incremental_load_properties_typeProperties_server": {
			"type": "string",
			"defaultValue": "studentdetails.database.windows.net"
		},
		"ls_incremental_load_properties_typeProperties_database": {
			"type": "string",
			"defaultValue": "student_details"
		},
		"ls_incremental_load_properties_typeProperties_userName": {
			"type": "string",
			"defaultValue": "Vinod"
		}
	},
	"variables": {
		"factoryId": "[concat('Microsoft.DataFactory/factories/', parameters('factoryName'))]"
	},
	"resources": [
		{
			"name": "[concat(parameters('factoryName'), '/Ls_increment_load')]",
			"type": "Microsoft.DataFactory/factories/linkedServices",
			"apiVersion": "2018-06-01",
			"properties": {
				"annotations": [],
				"type": "AzureBlobStorage",
				"typeProperties": {
					"connectionString": "[parameters('Ls_increment_load_connectionString')]"
				}
			},
			"dependsOn": []
		},
		{
			"name": "[concat(parameters('factoryName'), '/ls_1')]",
			"type": "Microsoft.DataFactory/factories/linkedServices",
			"apiVersion": "2018-06-01",
			"properties": {
				"annotations": [],
				"type": "AzureBlobStorage",
				"typeProperties": {
					"connectionString": "[parameters('ls_1_connectionString')]"
				}
			},
			"dependsOn": []
		},
		{
			"name": "[concat(parameters('factoryName'), '/ls_incremental_load')]",
			"type": "Microsoft.DataFactory/factories/linkedServices",
			"apiVersion": "2018-06-01",
			"properties": {
				"annotations": [],
				"type": "AzureSqlDatabase",
				"typeProperties": {
					"server": "[parameters('ls_incremental_load_properties_typeProperties_server')]",
					"database": "[parameters('ls_incremental_load_properties_typeProperties_database')]",
					"encrypt": "mandatory",
					"trustServerCertificate": false,
					"authenticationType": "SQL",
					"userName": "[parameters('ls_incremental_load_properties_typeProperties_userName')]",
					"password": {
						"type": "SecureString",
						"value": "[parameters('ls_incremental_load_password')]"
					}
				}
			},
			"dependsOn": []
		},
		{
			"name": "[concat(parameters('factoryName'), '/DelimitedText1')]",
			"type": "Microsoft.DataFactory/factories/datasets",
			"apiVersion": "2018-06-01",
			"properties": {
				"linkedServiceName": {
					"referenceName": "Ls_increment_load",
					"type": "LinkedServiceReference"
				},
				"annotations": [],
				"type": "DelimitedText",
				"typeProperties": {
					"location": {
						"type": "AzureBlobStorageLocation",
						"container": "destination"
					},
					"columnDelimiter": ",",
					"escapeChar": "\\",
					"firstRowAsHeader": true,
					"quoteChar": "\""
				},
				"schema": []
			},
			"dependsOn": [
				"[concat(variables('factoryId'), '/linkedServices/Ls_increment_load')]"
			]
		},
		{
			"name": "[concat(parameters('factoryName'), '/Json1')]",
			"type": "Microsoft.DataFactory/factories/datasets",
			"apiVersion": "2018-06-01",
			"properties": {
				"linkedServiceName": {
					"referenceName": "ls_1",
					"type": "LinkedServiceReference"
				},
				"annotations": [],
				"type": "Json",
				"typeProperties": {
					"location": {
						"type": "AzureBlobStorageLocation",
						"container": "destination"
					}
				},
				"schema": {}
			},
			"dependsOn": [
				"[concat(variables('factoryId'), '/linkedServices/ls_1')]"
			]
		},
		{
			"name": "[concat(parameters('factoryName'), '/ds_data_source_table')]",
			"type": "Microsoft.DataFactory/factories/datasets",
			"apiVersion": "2018-06-01",
			"properties": {
				"linkedServiceName": {
					"referenceName": "ls_incremental_load",
					"type": "LinkedServiceReference"
				},
				"annotations": [],
				"type": "AzureSqlTable",
				"schema": [
					{
						"name": "id",
						"type": "int",
						"precision": 10
					},
					{
						"name": "name",
						"type": "varchar"
					},
					{
						"name": "amount",
						"type": "decimal",
						"precision": 10,
						"scale": 2
					},
					{
						"name": "last_modified",
						"type": "datetime2",
						"scale": 7
					}
				],
				"typeProperties": {
					"schema": "dbo",
					"table": "data_source_table"
				}
			},
			"dependsOn": [
				"[concat(variables('factoryId'), '/linkedServices/ls_incremental_load')]"
			]
		},
		{
			"name": "[concat(parameters('factoryName'), '/ds_watermarktable')]",
			"type": "Microsoft.DataFactory/factories/datasets",
			"apiVersion": "2018-06-01",
			"properties": {
				"linkedServiceName": {
					"referenceName": "ls_incremental_load",
					"type": "LinkedServiceReference"
				},
				"annotations": [],
				"type": "AzureSqlTable",
				"schema": [
					{
						"name": "TableName",
						"type": "varchar"
					},
					{
						"name": "WatermarkValue",
						"type": "datetime2",
						"scale": 7
					}
				],
				"typeProperties": {
					"schema": "dbo",
					"table": "watermarktable"
				}
			},
			"dependsOn": [
				"[concat(variables('factoryId'), '/linkedServices/ls_incremental_load')]"
			]
		},
		{
			"name": "[concat(parameters('factoryName'), '/Pl_incremental_load')]",
			"type": "Microsoft.DataFactory/factories/pipelines",
			"apiVersion": "2018-06-01",
			"properties": {
				"activities": [
					{
						"name": "LookupOldwaterMarkValue",
						"type": "Lookup",
						"dependsOn": [],
						"policy": {
							"timeout": "0.12:00:00",
							"retry": 0,
							"retryIntervalInSeconds": 30,
							"secureOutput": false,
							"secureInput": false
						},
						"userProperties": [],
						"typeProperties": {
							"source": {
								"type": "AzureSqlSource",
								"queryTimeout": "02:00:00",
								"partitionOption": "None"
							},
							"dataset": {
								"referenceName": "ds_watermarktable",
								"type": "DatasetReference",
								"parameters": {}
							}
						}
					},
					{
						"name": "LookupNewwaterMarkValue",
						"type": "Lookup",
						"dependsOn": [],
						"policy": {
							"timeout": "0.12:00:00",
							"retry": 0,
							"retryIntervalInSeconds": 30,
							"secureOutput": false,
							"secureInput": false
						},
						"userProperties": [],
						"typeProperties": {
							"source": {
								"type": "AzureSqlSource",
								"sqlReaderQuery": "select max(last_modified) as new_Watermark_value from data_source_table",
								"queryTimeout": "02:00:00",
								"partitionOption": "None"
							},
							"dataset": {
								"referenceName": "ds_data_source_table",
								"type": "DatasetReference",
								"parameters": {}
							},
							"firstRowOnly": true
						}
					},
					{
						"name": "incremental_copyActivity",
						"type": "Copy",
						"dependsOn": [
							{
								"activity": "LookupOldwaterMarkValue",
								"dependencyConditions": [
									"Succeeded"
								]
							},
							{
								"activity": "LookupNewwaterMarkValue",
								"dependencyConditions": [
									"Succeeded"
								]
							}
						],
						"policy": {
							"timeout": "0.12:00:00",
							"retry": 0,
							"retryIntervalInSeconds": 30,
							"secureOutput": false,
							"secureInput": false
						},
						"userProperties": [],
						"typeProperties": {
							"source": {
								"type": "AzureSqlSource",
								"sqlReaderQuery": {
									"value": "select *\nfrom data_source_table\nwhere last_modified > '@{activity('LookupOldwaterMarkValue').output.firstRow.WatermarkValue}'\nand last_modified < '@{activity('LookupNewwaterMarkValue').output.firstRow.new_Watermark_value}'\n",
									"type": "Expression"
								},
								"queryTimeout": "02:00:00",
								"partitionOption": "None"
							},
							"sink": {
								"type": "DelimitedTextSink",
								"storeSettings": {
									"type": "AzureBlobStorageWriteSettings"
								},
								"formatSettings": {
									"type": "DelimitedTextWriteSettings",
									"quoteAllText": true,
									"fileExtension": ".txt"
								}
							},
							"enableStaging": false,
							"translator": {
								"type": "TabularTranslator",
								"typeConversion": true,
								"typeConversionSettings": {
									"allowDataTruncation": true,
									"treatBooleanAsNumber": false
								}
							}
						},
						"inputs": [
							{
								"referenceName": "ds_data_source_table",
								"type": "DatasetReference",
								"parameters": {}
							}
						],
						"outputs": [
							{
								"referenceName": "DelimitedText1",
								"type": "DatasetReference",
								"parameters": {}
							}
						]
					},
					{
						"name": "Stored procedure1",
						"type": "SqlServerStoredProcedure",
						"dependsOn": [
							{
								"activity": "incremental_copyActivity",
								"dependencyConditions": [
									"Succeeded"
								]
							}
						],
						"policy": {
							"timeout": "0.12:00:00",
							"retry": 0,
							"retryIntervalInSeconds": 30,
							"secureOutput": false,
							"secureInput": false
						},
						"userProperties": [],
						"typeProperties": {
							"storedProcedureName": "[[dbo].[usp_write_watermark]",
							"storedProcedureParameters": {
								"last_modified": {
									"value": {
										"value": "@{activity('LookupNewwaterMarkValue').output.firstRow.new_Watermark_value}",
										"type": "Expression"
									},
									"type": "DateTime"
								},
								"tablename": {
									"value": {
										"value": "@{activity('LookupOldwaterMarkValue').output.firstRow.tablename}",
										"type": "Expression"
									},
									"type": "String"
								}
							}
						},
						"linkedServiceName": {
							"referenceName": "ls_incremental_load",
							"type": "LinkedServiceReference"
						}
					}
				],
				"policy": {
					"elapsedTimeMetric": {}
				},
				"annotations": [],
				"lastPublishTime": "2026-02-06T16:15:19Z"
			},
			"dependsOn": [
				"[concat(variables('factoryId'), '/datasets/ds_watermarktable')]",
				"[concat(variables('factoryId'), '/datasets/ds_data_source_table')]",
				"[concat(variables('factoryId'), '/datasets/DelimitedText1')]",
				"[concat(variables('factoryId'), '/linkedServices/ls_incremental_load')]"
			]
		}
	]
}